fairies/__init__.py
fairies/classification_utils.py
fairies/knowledge.py
fairies/langconv.py
fairies/nlp_clean_data.py
fairies/nlp_jieba_utils.py
fairies/nlp_utils.py
fairies/read.py
fairies/setup.py
fairies/write.py
fairies/zh_wiki.py
fairies/fairies/__init__.py
fairies/fairies/classification_utils.py
fairies/fairies/knowledge.py
fairies/fairies/langconv.py
fairies/fairies/nlp_clean_data.py
fairies/fairies/nlp_jieba_utils.py
fairies/fairies/nlp_utils.py
fairies/fairies/read.py
fairies/fairies/write.py
fairies/fairies/zh_wiki.py
fairies-0.1.38.dist-info/METADATA
fairies-0.1.38.dist-info/WHEEL
fairies-0.1.38.dist-info/top_level.txt
fairies-0.1.38.dist-info/RECORD
