Metadata-Version: 2.1
Name: fairies
Version: 0.1.38
Summary: utils for nlp
Home-page: https://github.com/hgliyuhao/fairies
Author: liyuhao
Author-email: 1241225413@qq.com
License: Apache License 2.0
Requires-Dist: xlrd (==1.2.0)
Requires-Dist: jieba
Requires-Dist: xlwt
Requires-Dist: xlutils
Requires-Dist: matplotlib
Requires-Dist: pandas
Requires-Dist: orjson
Requires-Dist: xlsxwriter
Requires-Dist: scikit-learn
